irides/__init__.py
irides/design/__init__.py
irides/design/analog/__init__.py
irides/design/analog/bessel_inline_curvature.py
irides/design/analog/bessel_inline_slope.py
irides/design/analog/bessel_level.py
irides/design/analog/damped_oscillator.py
irides/design/analog/mbox_inline_curvature.py
irides/design/analog/mbox_inline_slope.py
irides/design/analog/mbox_level.py
irides/design/analog/polyema_composite_slope.py
irides/design/analog/polyema_inline_curvature.py
irides/design/analog/polyema_inline_slope.py
irides/design/analog/polyema_level.py
irides/design/digital/__init__.py
irides/design/digital/bessel_inline_curvature.py
irides/design/digital/bessel_inline_slope.py
irides/design/digital/bessel_jumpvol_level.py
irides/design/digital/bessel_level.py
irides/design/digital/damped_oscillator.py
irides/design/digital/mbox_inline_curvature.py
irides/design/digital/mbox_inline_slope.py
irides/design/digital/mbox_level.py
irides/design/digital/polyema_inline_curvature.py
irides/design/digital/polyema_inline_slope.py
irides/design/digital/polyema_jumpvol_level.py
irides/design/digital/polyema_level.py
irides/filter_signatures/__init__.py
irides/filter_signatures/analog/__init__.py
irides/filter_signatures/analog/bessel_inline_curvature.py
irides/filter_signatures/analog/bessel_inline_slope.py
irides/filter_signatures/analog/bessel_level.py
irides/filter_signatures/analog/damped_oscillator.py
irides/filter_signatures/analog/mbox_inline_curvature.py
irides/filter_signatures/analog/mbox_inline_slope.py
irides/filter_signatures/analog/mbox_level.py
irides/filter_signatures/analog/polyema_composite_slope.py
irides/filter_signatures/analog/polyema_inline_curvature.py
irides/filter_signatures/analog/polyema_inline_slope.py
irides/filter_signatures/analog/polyema_level.py
irides/filter_signatures/analog/unit_step.py
irides/filter_signatures/digital/__init__.py
irides/filter_signatures/digital/bessel_inline_curvature.py
irides/filter_signatures/digital/bessel_inline_slope.py
irides-1.0.2.dist-info/licenses/LICENSE
irides-1.0.2.dist-info/METADATA
irides-1.0.2.dist-info/WHEEL
irides-1.0.2.dist-info/top_level.txt
irides-1.0.2.dist-info/RECORD
