Metadata-Version: 2.4
Name: irides
Version: 1.0.2
Summary: Irides provides references implementations for select linear time-invariant filters.
Home-page: https://gitlab.com/irides-dev/irides
Author: Jay Damask
Author-email: jaydamask@buell-lane-press.co
License: Apache License 2.0
Project-URL: Documentation, https://gitlab.com/irides-dev/irides/
Project-URL: Changelog, https://gitlab.com/irides-dev/irides/
Project-URL: Issue Tracker, https://gitlab.com/irides-dev/irides/issues
Keywords: multivariate statistics
Classifier: Development Status :: 4 - Beta
Classifier: Environment :: Console
Classifier: Intended Audience :: Science/Research
Classifier: License :: OSI Approved :: Apache Software License
Classifier: Operating System :: OS Independent
Classifier: Programming Language :: Python :: 3.7
Classifier: Programming Language :: Python :: 3.8
Classifier: Programming Language :: Python :: 3.9
Classifier: Programming Language :: Python :: 3.10
Classifier: Programming Language :: Python :: 3.11
Classifier: Programming Language :: Python :: 3.12
Classifier: Topic :: Scientific/Engineering
Requires-Python: >=3.7
License-File: LICENSE
Requires-Dist: numpy>=1.23
Dynamic: author
Dynamic: author-email
Dynamic: classifier
Dynamic: description
Dynamic: description-content-type
Dynamic: home-page
Dynamic: keywords
Dynamic: license
Dynamic: license-file
Dynamic: project-url
Dynamic: requires-dist
Dynamic: requires-python
Dynamic: summary
